InitDecaytor/__init__.py
InitDecaytor/app.py
InitDecaytor/callbacks.py
InitDecaytor/csv_temperature_profile.py
InitDecaytor/decomposition.py
InitDecaytor/layout.py
initdecaytor-0.4.4.dist-info/licenses/LICENSE
initdecaytor-0.4.4.dist-info/METADATA
initdecaytor-0.4.4.dist-info/WHEEL
initdecaytor-0.4.4.dist-info/top_level.txt
initdecaytor-0.4.4.dist-info/RECORD
