Metadata-Version: 2.4
Name: InitDecaytor
Version: 0.4.4
Summary: Simulation of the thermal decomposition of free-radical initiators
Author-email: Kevin De Bruycker and Stijn D'hollander <kevindebruycker@gmail.com>
License-Expression: MIT
Classifier: Development Status :: 4 - Beta
Classifier: Operating System :: OS Independent
Classifier: Programming Language :: Python :: 3
Classifier: Programming Language :: Python :: 3.13
Requires-Python: >=3.8
License-File: LICENSE
Requires-Dist: dash>=3.0.4
Requires-Dist: matplotlib
Requires-Dist: numba
Requires-Dist: numpy
Requires-Dist: pandas
Requires-Dist: plotly
Requires-Dist: scipy
Dynamic: license-file
